py8583/__init__.py
py8583/py8583.py
py8583/py8583spec.py
py8583-1.3.dist-info/LICENSE
py8583-1.3.dist-info/METADATA
py8583-1.3.dist-info/WHEEL
py8583-1.3.dist-info/top_level.txt
py8583-1.3.dist-info/zip-safe
py8583-1.3.dist-info/RECORD
