Metadata-Version: 1.1
Name: py8583
Version: 1.3
Summary: ISO8583 python library
Home-page: https://github.com/alxnik/py8583
Author: Alexandros Nikolopoulos
Author-email: alxnik@gmail.com
License: LGPLv2
Keywords: ISO8583 banking protocol library
Platform: UNKNOWN
Classifier: License :: OSI Approved :: GNU Lesser General Public License v2 (LGPLv2)
Classifier: Operating System :: OS Independent
Classifier: Programming Language :: Python :: 2
Classifier: Programming Language :: Python :: 2.7
Classifier: Programming Language :: Python :: 3
Classifier: Programming Language :: Python :: 3.3
Classifier: Programming Language :: Python :: 3.4
Classifier: Programming Language :: Python :: 3.5
Classifier: Programming Language :: Python :: 3.6
Classifier: Topic :: Communications
Classifier: Intended Audience :: Developers
